lymia/__init__.py
lymia/_color_const.py
lymia/anim.py
lymia/colors.py
lymia/const.py
lymia/data.py
lymia/environment.py
lymia/errors.py
lymia/menu.py
lymia/panel.py
lymia/progress.py
lymia/runner.py
lymia/scene.py
lymia/screen.py
lymia/utils.py
lymia/forms/__init__.py
lymia/forms/_base.py
lymia/forms/password.py
lymia/forms/text.py
lymia-0.0.5.dist-info/licenses/LICENSE
lymia-0.0.5.dist-info/METADATA
lymia-0.0.5.dist-info/WHEEL
lymia-0.0.5.dist-info/top_level.txt
lymia-0.0.5.dist-info/zip-safe
lymia-0.0.5.dist-info/RECORD
