Metadata-Version: 2.4
Name: lymia
Version: 0.0.5
Summary: Easy to use curses wrapper
Home-page: https://github.com/RimuEirnarn/lymia
Author: RimuEirnarn
Author-email: Rimu Eirnarn <rimuru720@proton.me>
License-Expression: BSD-3-Clause
Project-URL: Homepage, https://github.com/RimuEirnarn/lymia
Project-URL: Repository, https://github.com/RimuEirnarn/lymia
Keywords: curses
Classifier: Programming Language :: Python :: 3.13
Classifier: Programming Language :: Python :: Implementation :: CPython
Requires-Python: >=3.13
License-File: LICENSE
Provides-Extra: dev
Requires-Dist: pytest; extra == "dev"
Requires-Dist: pylint; extra == "dev"
Requires-Dist: black; extra == "dev"
Provides-Extra: docs
Requires-Dist: sphinx; extra == "docs"
Requires-Dist: myst_parser; extra == "docs"
Dynamic: license-file
